g/__about__.py
g/__init__.py
g-0.0.9.dist-info/METADATA
g-0.0.9.dist-info/WHEEL
g-0.0.9.dist-info/entry_points.txt
g-0.0.9.dist-info/licenses/LICENSE
g-0.0.9.dist-info/RECORD
