Metadata-Version: 2.4
Name: g
Version: 0.0.9
Summary: cli command to easily sync current directory
Project-URL: Bug Tracker, https://github.com/vcs-python/g/issues
Project-URL: Documentation, https://g.git-pull.com
Project-URL: Repository, https://github.com/vcs-python/g
Project-URL: Changes, https://github.com/vcs-python/g/blob/master/CHANGES
Author-email: Tony Narlock <tony@git-pull.com>
License: MIT
License-File: LICENSE
Keywords: cli,g,git,libvcs,mercurial,pull,svn,sync,update,vcs
Classifier: Development Status :: 4 - Beta
Classifier: Environment :: Web Environment
Classifier: Intended Audience :: Developers
Classifier: License :: OSI Approved :: MIT License
Classifier: Operating System :: MacOS :: MacOS X
Classifier: Operating System :: POSIX
Classifier: Programming Language :: Python
Classifier: Programming Language :: Python :: 3
Classifier: Programming Language :: Python :: 3.10
Classifier: Programming Language :: Python :: 3.11
Classifier: Programming Language :: Python :: 3.12
Classifier: Programming Language :: Python :: 3.13
Classifier: Programming Language :: Python :: 3.14
Classifier: Topic :: System :: Shells
Classifier: Topic :: Utilities
Requires-Python: <4.0,>=3.10
